odoo/addons/stock_move_purchase_uom/README.rst
odoo/addons/stock_move_purchase_uom/__init__.py
odoo/addons/stock_move_purchase_uom/__manifest__.py
odoo/addons/stock_move_purchase_uom/i18n/it.po
odoo/addons/stock_move_purchase_uom/i18n/stock_move_purchase_uom.pot
odoo/addons/stock_move_purchase_uom/models/__init__.py
odoo/addons/stock_move_purchase_uom/models/stock_move.py
odoo/addons/stock_move_purchase_uom/models/stock_move_line.py
odoo/addons/stock_move_purchase_uom/models/stock_picking_type.py
odoo/addons/stock_move_purchase_uom/readme/CONTRIBUTORS.md
odoo/addons/stock_move_purchase_uom/readme/DESCRIPTION.md
odoo/addons/stock_move_purchase_uom/static/description/icon.png
odoo/addons/stock_move_purchase_uom/static/description/index.html
odoo/addons/stock_move_purchase_uom/tests/__init__.py
odoo/addons/stock_move_purchase_uom/tests/test_common.py
odoo/addons/stock_move_purchase_uom/tests/test_stock_move.py
odoo/addons/stock_move_purchase_uom/tests/test_stock_move_line.py
odoo/addons/stock_move_purchase_uom/tests/test_stock_move_purchase_uom.py
odoo/addons/stock_move_purchase_uom/views/stock_picking_type_views.xml
odoo_addon_stock_move_purchase_uom-18.0.1.1.0.3.dist-info/METADATA
odoo_addon_stock_move_purchase_uom-18.0.1.1.0.3.dist-info/WHEEL
odoo_addon_stock_move_purchase_uom-18.0.1.1.0.3.dist-info/top_level.txt
odoo_addon_stock_move_purchase_uom-18.0.1.1.0.3.dist-info/RECORD
